gRPCNvidia/__init__.py
gRPCNvidia-0.0.1.dist-info/METADATA
gRPCNvidia-0.0.1.dist-info/WHEEL
gRPCNvidia-0.0.1.dist-info/top_level.txt
gRPCNvidia-0.0.1.dist-info/RECORD
