Metadata-Version: 2.1
Name: gRPCNvidia
Version: 0.0.1
Summary: Nvidia gRPC module for hosting servers/clients using gRPC for Python 3.6+
Home-page: https://github.com/OmarSiwy/gRPCNvidia
Author: Omar
Author-email: ok.elsawy@gmail.com
Classifier: Programming Language :: Python :: 3
Classifier: License :: OSI Approved :: MIT License
Classifier: Operating System :: OS Independent
Requires-Python: >=3.6
